mlvispy/__init__.py
mlvispy/class_builder.py
mlvispy-0.0.1.data/data/share/jupyter/nbextensions/mlvispy/index.js
mlvispy-0.0.1.dist-info/METADATA
mlvispy-0.0.1.dist-info/WHEEL
mlvispy-0.0.1.dist-info/top_level.txt
mlvispy-0.0.1.dist-info/RECORD
