Metadata-Version: 2.1
Name: mlvispy
Version: 0.0.1
Summary: A wrapper around react components for use in jupyter notebooks
Home-page: https://github.com/
Author: Hong Wang
Author-email: hongw@uber.com
License: MIT
Platform: UNKNOWN
Requires-Python: >=3.7
Requires-Dist: ipython
Requires-Dist: jupyter-react
